{"exercises": [{"name": "dumbbell pushups", "muscle_group": "Other", "created_at": "2025-02-24T16:45:46.517614"}, {"name": "face pull", "muscle_group": "Other", "created_at": "2025-02-24T16:45:46.517614"}, {"name": "overhead dumbbell", "muscle_group": "Other", "created_at": "2025-02-24T16:45:46.517614"}, {"name": "pull ups", "muscle_group": "Other", "created_at": "2025-02-24T16:45:46.517614"}, {"name": "pulldown", "muscle_group": "Other", "created_at": "2025-02-24T16:45:46.517614"}, {"name": "seared row", "muscle_group": "Other", "created_at": "2025-02-24T16:45:46.517614"}, {"name": "strange bent pull", "muscle_group": "Other", "created_at": "2025-02-24T16:45:46.517614"}, {"name": "triceps", "muscle_group": "Other", "created_at": "2025-02-24T16:45:46.517614"}]}